zeose-0.0.1.dist-info/licenses/LICENSE
zse/__init__.py
zse/cation.py
zse/cation_utilities.py
zse/cif_tools.py
zse/proton_utilities.py
zse/protonate.py
zse/ring_utilities.py
zse/ring_validation.py
zse/rings.py
zse/substitute.py
zse/tpairs.py
zse/utilities.py
zse/collections/__init__.py
zse/collections/framework.py
zse/collections/frameworks.db
zse/collections/frameworks_old.db
zeose-0.0.1.dist-info/METADATA
zeose-0.0.1.dist-info/WHEEL
zeose-0.0.1.dist-info/top_level.txt
zeose-0.0.1.dist-info/RECORD
