Metadata-Version: 2.4
Name: zeose
Version: 0.0.1
Summary: A package with functions that automate zeolite structure building processes
Author-email: Jerry Crum <jcrum@nd.edu>, Alex Hoffman <ahoffman2011@gmail.com>
License-Expression: MIT
Project-URL: Homepage, https://github.com/jtcrum/zse
Project-URL: Issues, https://github.com/jtcrum/zse/issues
Classifier: Programming Language :: Python :: 3
Classifier: Operating System :: OS Independent
Classifier: Topic :: Scientific/Engineering :: Chemistry
Classifier: Topic :: Scientific/Engineering :: Physics
Classifier: Intended Audience :: Science/Research
Requires-Python: >=3.10
License-File: LICENSE
Requires-Dist: numpy
Requires-Dist: ase
Requires-Dist: networkx
Requires-Dist: jupyter>=1.1.1
Requires-Dist: ipython>=8.37.0
Provides-Extra: dev
Requires-Dist: pytest; extra == "dev"
Requires-Dist: pytest-cov; extra == "dev"
Requires-Dist: ruff; extra == "dev"
Requires-Dist: mypy; extra == "dev"
Requires-Dist: pre-commit; extra == "dev"
Dynamic: license-file
